{
  "mapId": 1,
  "ropesData": [
    {
      "listParticles": [
        {
          "particles": [
            {
              "position": {
                "x": 1.5,
                "y": 0.20000000298023224,
                "z": 2.5000057220458984
              }
            },
            {
              "position": {
                "x": 1.4836938381195068,
                "y": 0.44683390855789185,
                "z": 2.456122875213623
              }
            },
            {
              "position": {
                "x": 1.4570013284683228,
                "y": 0.4258373975753784,
                "z": 2.380213499069214
              }
            },
            {
              "position": {
                "x": 1.39190673828125,
                "y": 0.37428733706474304,
                "z": 2.1873507499694824
              }
            },
            {
              "position": {
                "x": 1.3515688180923462,
                "y": 0.3506220281124115,
                "z": 2.0617175102233887
              }
            },
            {
              "position": {
                "x": 1.3091497421264648,
                "y": 0.3311413526535034,
                "z": 1.936779499053955
              }
            },
            {
              "position": {
                "x": 1.2657549381256104,
                "y": 0.31734710931777954,
                "z": 1.8103996515274048
              }
            },
            {
              "position": {
                "x": 1.2216171026229858,
                "y": 0.3188042640686035,
                "z": 1.6843072175979614
              }
            },
            {
              "position": {
                "x": 1.1898912191390991,
                "y": 0.3638513684272766,
                "z": 1.5633594989776611
              }
            },
            {
              "position": {
                "x": 1.1597262620925903,
                "y": 0.4181436598300934,
                "z": 1.4457995891571045
              }
            },
            {
              "position": {
                "x": 1.1157366037368774,
                "y": 0.45770812034606934,
                "z": 1.3212178945541382
              }
            },
            {
              "position": {
                "x": 1.0327786207199097,
                "y": 0.4160071313381195,
                "z": 1.2145825624465942
              }
            },
            {
              "position": {
                "x": 0.9503123164176941,
                "y": 0.3056730329990387,
                "z": 1.187425971031189
              }
            },
            {
              "position": {
                "x": 0.8880411386489868,
                "y": 0.20513679087162018,
                "z": 1.263193130493164
              }
            },
            {
              "position": {
                "x": 0.8444550037384033,
                "y": 0.20002441108226776,
                "z": 1.4039607048034668
              }
            },
            {
              "position": {
                "x": 0.8341520428657532,
                "y": 0.22970269620418549,
                "z": 1.5339596271514893
              }
            },
            {
              "position": {
                "x": 0.7859517931938171,
                "y": 0.260492742061615,
                "z": 1.6556984186172485
              }
            },
            {
              "position": {
                "x": 0.7020394802093506,
                "y": 0.2760174572467804,
                "z": 1.7599642276763916
              }
            },
            {
              "position": {
                "x": 0.6158052682876587,
                "y": 0.29206782579421997,
                "z": 1.8627204895019531
              }
            },
            {
              "position": {
                "x": 0.5320129990577698,
                "y": 0.31346356868743896,
                "z": 1.9668203592300415
              }
            },
            {
              "position": {
                "x": 0.4776959717273712,
                "y": 0.34819918870925903,
                "z": 2.09690523147583
              }
            },
            {
              "position": {
                "x": 0.4964132606983185,
                "y": 0.3694460093975067,
                "z": 2.1803975105285645
              }
            },
            {
              "position": {
                "x": 0.5685020089149475,
                "y": 0.4176379442214966,
                "z": 2.3052315711975098
              }
            },
            {
              "position": {
                "x": 0.5,
                "y": 0.20000000298023224,
                "z": 2.5
              }
            }
          ],
          "scale": 1.0,
          "colorId": 5
        },
        {
          "particles": [
            {
              "position": {
                "x": 0.5,
                "y": 0.20000000298023224,
                "z": 2.5000057220458984
              }
            },
            {
              "position": {
                "x": 0.37296774983406067,
                "y": 0.4206131398677826,
                "z": 2.3425278663635254
              }
            },
            {
              "position": {
                "x": 0.34978407621383667,
                "y": 0.39853209257125854,
                "z": 2.2656054496765137
              }
            },
            {
              "position": {
                "x": 0.3138318359851837,
                "y": 0.3899509012699127,
                "z": 2.19091796875
              }
            },
            {
              "position": {
                "x": 0.26841121912002563,
                "y": 0.3704892098903656,
                "z": 2.1304664611816406
              }
            },
            {
              "position": {
                "x": 0.13550911843776703,
                "y": 0.3348875045776367,
                "z": 1.9534448385238647
              }
            },
            {
              "position": {
                "x": 0.048087574541568756,
                "y": 0.3194584846496582,
                "z": 1.8351287841796875
              }
            },
            {
              "position": {
                "x": 0.004507184028625488,
                "y": 0.3147430717945099,
                "z": 1.7761075496673584
              }
            },
            {
              "position": {
                "x": -0.08270536363124847,
                "y": 0.3110096752643585,
                "z": 1.6584550142288208
              }
            },
            {
              "position": {
                "x": -0.17017734050750732,
                "y": 0.31330177187919617,
                "z": 1.5411126613616943
              }
            },
            {
              "position": {
                "x": -0.2148253321647644,
                "y": 0.3150644898414612,
                "z": 1.4827228784561157
              }
            },
            {
              "position": {
                "x": -0.2501375675201416,
                "y": 0.3302795886993408,
                "z": 1.417382836341858
              }
            },
            {
              "position": {
                "x": -0.3051605224609375,
                "y": 0.3547734320163727,
                "z": 1.3606616258621216
              }
            },
            {
              "position": {
                "x": -0.45136478543281555,
                "y": 0.3862525522708893,
                "z": 1.3058180809020996
              }
            },
            {
              "position": {
                "x": -0.6087095737457275,
                "y": 0.3859160542488098,
                "z": 1.3187052011489868
              }
            },
            {
              "position": {
                "x": -0.7594801187515259,
                "y": 0.39048951864242554,
                "z": 1.3499424457550049
              }
            },
            {
              "position": {
                "x": -0.8356314897537231,
                "y": 0.39429065585136414,
                "z": 1.3656710386276245
              }
            },
            {
              "position": {
                "x": -1.0609980821609497,
                "y": 0.4137915372848511,
                "z": 1.4131901264190674
              }
            },
            {
              "position": {
                "x": -1.2118781805038452,
                "y": 0.4316488802433014,
                "z": 1.4446723461151123
              }
            },
            {
              "position": {
                "x": -1.2893675565719604,
                "y": 0.4405587613582611,
                "z": 1.4598300457000732
              }
            },
            {
              "position": {
                "x": -1.4456894397735596,
                "y": 0.48031842708587646,
                "z": 1.4896341562271118
              }
            },
            {
              "position": {
                "x": -1.5,
                "y": 0.20000000298023224,
                "z": 1.5
              }
            }
          ],
          "scale": 1.0,
          "colorId": 5
        }
      ],
      "pinsData": [
        {
          "position": {
            "x": 1.5,
            "z": 2.5
          },
          "isLocked": 1
        },
        {
          "position": {
            "x": 0.5,
            "z": 2.5
          }
        },
        {
          "position": {
            "x": -1.5,
            "z": 1.5
          }
        },
        {
          "position": {
            "x": -0.5899658203125,
            "z": 1.8199996948242188
          }
        },
        {
          "position": {
            "x": -0.5899658203125,
            "z": 1.8199996948242188
          }
        }
      ],
      "colorId": 5
    },
    {
      "listParticles": [
        {
          "particles": [
            {
              "position": {
                "x": 0.5,
                "y": 0.20000000298023224,
                "z": -1.5
              }
            },
            {
              "position": {
                "x": 0.48269274830818176,
                "y": 0.4798387885093689,
                "z": -1.4444246292114258
              }
            },
            {
              "position": {
                "x": 0.4338056445121765,
                "y": 0.43109315633773804,
                "z": -1.2855746746063232
              }
            },
            {
              "position": {
                "x": 0.4099636673927307,
                "y": 0.4181027412414551,
                "z": -1.207069754600525
              }
            },
            {
              "position": {
                "x": 0.3426739275455475,
                "y": 0.38229450583457947,
                "z": -0.9728487133979797
              }
            },
            {
              "position": {
                "x": 0.2993314862251282,
                "y": 0.3643580675125122,
                "z": -0.8172615766525269
              }
            },
            {
              "position": {
                "x": 0.2787550985813141,
                "y": 0.35803285241127014,
                "z": -0.739763617515564
              }
            },
            {
              "position": {
                "x": 0.23319457471370697,
                "y": 0.34503334760665894,
                "z": -0.5850061774253845
              }
            },
            {
              "position": {
                "x": 0.2092418074607849,
                "y": 0.3192213475704193,
                "z": -0.4253072738647461
              }
            },
            {
              "position": {
                "x": 0.19324079155921936,
                "y": 0.29542335867881775,
                "z": -0.26556217670440674
              }
            },
            {
              "position": {
                "x": 0.25394150614738464,
                "y": 0.3300337493419647,
                "z": -0.11335895210504532
              }
            },
            {
              "position": {
                "x": 0.4131786525249481,
                "y": 0.39737993478775024,
                "z": -0.06713132560253143
              }
            },
            {
              "position": {
                "x": 0.5563583374023438,
                "y": 0.37202632427215576,
                "z": -0.13934800028800964
              }
            },
            {
              "position": {
                "x": 0.6560594439506531,
                "y": 0.32830941677093506,
                "z": -0.24507538974285126
              }
            },
            {
              "position": {
                "x": 0.7575508952140808,
                "y": 0.32725000381469727,
                "z": -0.3617173731327057
              }
            },
            {
              "position": {
                "x": 0.8543097972869873,
                "y": 0.3261333107948303,
                "z": -0.4825112819671631
              }
            },
            {
              "position": {
                "x": 0.9503737092018127,
                "y": 0.3273782432079315,
                "z": -0.605522096157074
              }
            },
            {
              "position": {
                "x": 1.043002963066101,
                "y": 0.3317604959011078,
                "z": -0.7305626273155212
              }
            },
            {
              "position": {
                "x": 1.1334155797958374,
                "y": 0.34045493602752686,
                "z": -0.8575056195259094
              }
            },
            {
              "position": {
                "x": 1.2223418951034546,
                "y": 0.3545779287815094,
                "z": -0.9862700700759888
              }
            },
            {
              "position": {
                "x": 1.3097103834152222,
                "y": 0.3732427954673767,
                "z": -1.1160045862197876
              }
            },
            {
              "position": {
                "x": 1.3966060876846313,
                "y": 0.3964153230190277,
                "z": -1.2461894750595093
              }
            },
            {
              "position": {
                "x": 1.4390403032302856,
                "y": 0.4195110499858856,
                "z": -1.3074268102645874
              }
            },
            {
              "position": {
                "x": 1.5,
                "y": 0.20000000298023224,
                "z": -1.4999942779541016
              }
            }
          ],
          "scale": 1.0,
          "colorId": 5
        },
        {
          "particles": [
            {
              "position": {
                "x": 1.5,
                "y": 0.20000000298023224,
                "z": -1.5
              }
            },
            {
              "position": {
                "x": 1.2974730730056763,
                "y": 0.4198625385761261,
                "z": -1.4815131425857544
              }
            },
            {
              "position": {
                "x": 1.2418415546417236,
                "y": 0.3865134119987488,
                "z": -1.4559881687164307
              }
            },
            {
              "position": {
                "x": 1.121700406074524,
                "y": 0.34817561507225037,
                "z": -1.403855800628662
              }
            },
            {
              "position": {
                "x": 1.0040695667266846,
                "y": 0.3149029016494751,
                "z": -1.3532514572143555
              }
            },
            {
              "position": {
                "x": 0.8836415410041809,
                "y": 0.2873087525367737,
                "z": -1.3026123046875
              }
            },
            {
              "position": {
                "x": 0.7632624506950378,
                "y": 0.263352632522583,
                "z": -1.2514519691467285
              }
            },
            {
              "position": {
                "x": 0.6398941278457642,
                "y": 0.24481844902038574,
                "z": -1.1985359191894531
              }
            },
            {
              "position": {
                "x": 0.5079581141471863,
                "y": 0.2260446399450302,
                "z": -1.1621267795562744
              }
            },
            {
              "position": {
                "x": 0.37130534648895264,
                "y": 0.20766858756542206,
                "z": -1.1491265296936035
              }
            },
            {
              "position": {
                "x": 0.23503722250461578,
                "y": 0.20149417221546173,
                "z": -1.13319730758667
              }
            },
            {
              "position": {
                "x": 0.09744234383106232,
                "y": 0.20002439618110657,
                "z": -1.1165204048156738
              }
            },
            {
              "position": {
                "x": -0.1693698763847351,
                "y": 0.20002441108226776,
                "z": -1.0798163414001465
              }
            },
            {
              "position": {
                "x": -0.300828218460083,
                "y": 0.20002441108226776,
                "z": -1.0596412420272827
              }
            },
            {
              "position": {
                "x": -0.4326450228691101,
                "y": 0.20113961398601532,
                "z": -1.039337158203125
              }
            },
            {
              "position": {
                "x": -0.5585548877716064,
                "y": 0.2414913773536682,
                "z": -1.013275146484375
              }
            },
            {
              "position": {
                "x": -0.6308369636535645,
                "y": 0.349490225315094,
                "z": -0.9614253044128418
              }
            },
            {
              "position": {
                "x": -0.6246411800384521,
                "y": 0.46280956268310547,
                "z": -0.8685788512229919
              }
            },
            {
              "position": {
                "x": -0.5716428756713867,
                "y": 0.501688539981842,
                "z": -0.7321721911430359
              }
            },
            {
              "position": {
                "x": -0.5295712351799011,
                "y": 0.4539966583251953,
                "z": -0.598981499671936
              }
            },
            {
              "position": {
                "x": -0.511070728302002,
                "y": 0.447903037071228,
                "z": -0.536411464214325
              }
            },
            {
              "position": {
                "x": -0.5,
                "y": 0.20000000298023224,
                "z": -0.49999427795410156
              }
            }
          ],
          "scale": 1.0,
          "colorId": 5
        }
      ],
      "pinsData": [
        {
          "position": {
            "x": 0.5,
            "z": -1.5
          }
        },
        {
          "position": {
            "x": 1.5,
            "z": -1.5
          }
        },
        {
          "position": {
            "x": -0.5,
            "z": -0.5
          },
          "isLocked": 1
        },
        {
          "position": {
            "x": -0.5899658203125,
            "z": 1.8199996948242188
          }
        },
        {
          "position": {
            "x": -0.5899658203125,
            "z": 1.8199996948242188
          }
        }
      ],
      "colorId": 5
    },
    {
      "listParticles": [
        {
          "particles": [
            {
              "position": {
                "x": -0.5,
                "y": 0.20000000298023224,
                "z": 0.5
              }
            },
            {
              "position": {
                "x": -0.4649692475795746,
                "y": 0.48113951086997986,
                "z": 0.4644715189933777
              }
            },
            {
              "position": {
                "x": -0.32660573720932007,
                "y": 0.4453408718109131,
                "z": 0.3244287371635437
              }
            },
            {
              "position": {
                "x": -0.27513134479522705,
                "y": 0.4479691982269287,
                "z": 0.2731878161430359
              }
            },
            {
              "position": {
                "x": -0.17286933958530426,
                "y": 0.4579067826271057,
                "z": 0.17148324847221375
              }
            },
            {
              "position": {
                "x": -0.11941983550786972,
                "y": 0.46515804529190063,
                "z": 0.12028692662715912
              }
            },
            {
              "position": {
                "x": 0.04875728487968445,
                "y": 0.4840357303619385,
                "z": -0.03569594770669937
              }
            },
            {
              "position": {
                "x": 0.15917587280273438,
                "y": 0.5027649402618408,
                "z": -0.1399846225976944
              }
            },
            {
              "position": {
                "x": 0.2854847013950348,
                "y": 0.4775446355342865,
                "z": -0.23469534516334534
              }
            },
            {
              "position": {
                "x": 0.3818497657775879,
                "y": 0.3481580913066864,
                "z": -0.2487599402666092
              }
            },
            {
              "position": {
                "x": 0.40616488456726074,
                "y": 0.2120751589536667,
                "z": -0.14620111882686615
              }
            },
            {
              "position": {
                "x": 0.3848487138748169,
                "y": 0.20002441108226776,
                "z": -0.00025358120910823345
              }
            },
            {
              "position": {
                "x": 0.34785622358322144,
                "y": 0.20002439618110657,
                "z": 0.13812536001205444
              }
            },
            {
              "position": {
                "x": 0.28849542140960693,
                "y": 0.20002439618110657,
                "z": 0.34642717242240906
              }
            },
            {
              "position": {
                "x": 0.24517351388931274,
                "y": 0.21011552214622498,
                "z": 0.478886216878891
              }
            },
            {
              "position": {
                "x": 0.23776237666606903,
                "y": 0.23609133064746857,
                "z": 0.6183241009712219
              }
            },
            {
              "position": {
                "x": 0.2552083134651184,
                "y": 0.2741919159889221,
                "z": 0.7570960521697998
              }
            },
            {
              "position": {
                "x": 0.27183249592781067,
                "y": 0.31786754727363586,
                "z": 0.8970551490783691
              }
            },
            {
              "position": {
                "x": 0.287153422832489,
                "y": 0.36411696672439575,
                "z": 1.0364793539047241
              }
            },
            {
              "position": {
                "x": 0.3039100766181946,
                "y": 0.4128510653972626,
                "z": 1.175992727279663
              }
            },
            {
              "position": {
                "x": 0.32256433367729187,
                "y": 0.41230258345603943,
                "z": 1.3244059085845947
              }
            },
            {
              "position": {
                "x": 0.32777243852615356,
                "y": 0.4207339286804199,
                "z": 1.394570231437683
              }
            },
            {
              "position": {
                "x": 0.5,
                "y": 0.20000000298023224,
                "z": 1.5000057220458984
              }
            }
          ],
          "scale": 1.0,
          "colorId": 2
        },
        {
          "particles": [
            {
              "position": {
                "x": 0.5,
                "y": 0.20000000298023224,
                "z": 1.5000057220458984
              }
            },
            {
              "position": {
                "x": 0.5449364185333252,
                "y": 0.4426432251930237,
                "z": 1.2964646816253662
              }
            },
            {
              "position": {
                "x": 0.5465260148048401,
                "y": 0.4410874545574188,
                "z": 1.214141607284546
              }
            },
            {
              "position": {
                "x": 0.5607298016548157,
                "y": 0.4058438539505005,
                "z": 1.0553206205368042
              }
            },
            {
              "position": {
                "x": 0.5868628025054932,
                "y": 0.33721500635147095,
                "z": 0.8245960474014282
              }
            },
            {
              "position": {
                "x": 0.6031328439712524,
                "y": 0.298780232667923,
                "z": 0.6713099479675293
              }
            },
            {
              "position": {
                "x": 0.5837599039077759,
                "y": 0.3458828032016754,
                "z": 0.5127905607223511
              }
            },
            {
              "position": {
                "x": 0.47031691670417786,
                "y": 0.39334073662757874,
                "z": 0.40659159421920776
              }
            },
            {
              "position": {
                "x": 0.3335936665534973,
                "y": 0.3923889100551605,
                "z": 0.3377605974674225
              }
            },
            {
              "position": {
                "x": 0.19692863523960114,
                "y": 0.36354154348373413,
                "z": 0.2674625813961029
              }
            },
            {
              "position": {
                "x": 0.06746172159910202,
                "y": 0.31553858518600464,
                "z": 0.19926327466964722
              }
            },
            {
              "position": {
                "x": -0.05996356159448624,
                "y": 0.27401354908943176,
                "z": 0.12928229570388794
              }
            },
            {
              "position": {
                "x": -0.18839804828166962,
                "y": 0.24861374497413635,
                "z": 0.05836121737957001
              }
            },
            {
              "position": {
                "x": -0.3139263391494751,
                "y": 0.22916387021541595,
                "z": -0.012340913526713848
              }
            },
            {
              "position": {
                "x": -0.43823927640914917,
                "y": 0.2153470814228058,
                "z": -0.08283429592847824
              }
            },
            {
              "position": {
                "x": -0.5605238080024719,
                "y": 0.20655211806297302,
                "z": -0.1528974026441574
              }
            },
            {
              "position": {
                "x": -0.6839230060577393,
                "y": 0.20417577028274536,
                "z": -0.22102560102939606
              }
            },
            {
              "position": {
                "x": -0.7935509085655212,
                "y": 0.20002439618110657,
                "z": -0.3079625964164734
              }
            },
            {
              "position": {
                "x": -0.9087036848068237,
                "y": 0.21719561517238617,
                "z": -0.3879544138908386
              }
            },
            {
              "position": {
                "x": -1.018320918083191,
                "y": 0.3132922053337097,
                "z": -0.41931772232055664
              }
            },
            {
              "position": {
                "x": -1.161218523979187,
                "y": 0.37451887130737305,
                "z": -0.3847270905971527
              }
            },
            {
              "position": {
                "x": -1.3069242238998413,
                "y": 0.4151476323604584,
                "z": -0.4178251326084137
              }
            },
            {
              "position": {
                "x": -1.447943925857544,
                "y": 0.4804134964942932,
                "z": -0.4790382981300354
              }
            },
            {
              "position": {
                "x": -1.5,
                "y": 0.20000000298023224,
                "z": -0.5
              }
            }
          ],
          "scale": 1.0,
          "colorId": 2
        }
      ],
      "pinsData": [
        {
          "position": {
            "x": -0.5,
            "z": 0.5
          }
        },
        {
          "position": {
            "x": 0.5,
            "z": 1.5
          }
        },
        {
          "position": {
            "x": -1.5,
            "z": -0.5
          }
        },
        {
          "position": {
            "x": -0.5899658203125,
            "z": 1.8199996948242188
          }
        },
        {
          "position": {
            "x": -0.5899658203125,
            "z": 1.8199996948242188
          }
        }
      ],
      "colorId": 2
    },
    {
      "listParticles": [
        {
          "particles": [
            {
              "position": {
                "x": -0.5,
                "y": 0.20000000298023224,
                "z": 1.5
              }
            },
            {
              "position": {
                "x": -0.4649471938610077,
                "y": 0.44791463017463684,
                "z": 1.4977041482925415
              }
            },
            {
              "position": {
                "x": -0.33933112025260925,
                "y": 0.502199113368988,
                "z": 1.4871271848678589
              }
            },
            {
              "position": {
                "x": -0.27072873711586,
                "y": 0.5190117955207825,
                "z": 1.4685826301574707
              }
            },
            {
              "position": {
                "x": -0.13804960250854492,
                "y": 0.48898595571517944,
                "z": 1.4145601987838745
              }
            },
            {
              "position": {
                "x": -0.028974266722798347,
                "y": 0.4105602502822876,
                "z": 1.3665565252304077
              }
            },
            {
              "position": {
                "x": 0.079330675303936,
                "y": 0.33540257811546326,
                "z": 1.3180367946624756
              }
            },
            {
              "position": {
                "x": 0.1870240867137909,
                "y": 0.26467055082321167,
                "z": 1.2701685428619385
              }
            },
            {
              "position": {
                "x": 0.30568134784698486,
                "y": 0.21970728039741516,
                "z": 1.2199302911758423
              }
            },
            {
              "position": {
                "x": 0.4302329421043396,
                "y": 0.23413950204849243,
                "z": 1.1716578006744385
              }
            },
            {
              "position": {
                "x": 0.5656095147132874,
                "y": 0.24514897167682648,
                "z": 1.1743206977844238
              }
            },
            {
              "position": {
                "x": 0.6774868965148926,
                "y": 0.2903551757335663,
                "z": 1.2364016771316528
              }
            },
            {
              "position": {
                "x": 0.7731295824050903,
                "y": 0.3615902066230774,
                "z": 1.3032433986663818
              }
            },
            {
              "position": {
                "x": 0.9010756611824036,
                "y": 0.3731774687767029,
                "z": 1.365301251411438
              }
            },
            {
              "position": {
                "x": 1.0238322019577026,
                "y": 0.29599085450172424,
                "z": 1.3687158823013306
              }
            },
            {
              "position": {
                "x": 1.1214125156402588,
                "y": 0.2556840479373932,
                "z": 1.287476897239685
              }
            },
            {
              "position": {
                "x": 1.1943491697311401,
                "y": 0.2614991366863251,
                "z": 1.1768183708190918
              }
            },
            {
              "position": {
                "x": 1.2297345399856567,
                "y": 0.2673291862010956,
                "z": 1.1205871105194092
              }
            },
            {
              "position": {
                "x": 1.2649585008621216,
                "y": 0.2746770679950714,
                "z": 1.064656376838684
              }
            },
            {
              "position": {
                "x": 1.3375887870788574,
                "y": 0.29701048135757446,
                "z": 0.954677939414978
              }
            },
            {
              "position": {
                "x": 1.408974051475525,
                "y": 0.33636295795440674,
                "z": 0.8503352999687195
              }
            },
            {
              "position": {
                "x": 1.475199818611145,
                "y": 0.376769483089447,
                "z": 0.7518733143806458
              }
            },
            {
              "position": {
                "x": 1.5091053247451782,
                "y": 0.41617551445961,
                "z": 0.7064077854156494
              }
            },
            {
              "position": {
                "x": 1.5,
                "y": 0.20000000298023224,
                "z": 0.5000057220458984
              }
            }
          ],
          "scale": 1.0,
          "colorId": 1
        },
        {
          "particles": [
            {
              "position": {
                "x": 1.5,
                "y": 0.20000000298023224,
                "z": 0.5000057220458984
              }
            },
            {
              "position": {
                "x": 1.3099565505981445,
                "y": 0.4409531056880951,
                "z": 0.4790917634963989
              }
            },
            {
              "position": {
                "x": 1.2667253017425537,
                "y": 0.4228057563304901,
                "z": 0.4886631965637207
              }
            },
            {
              "position": {
                "x": 1.1415876150131226,
                "y": 0.3802811801433563,
                "z": 0.5172253847122192
              }
            },
            {
              "position": {
                "x": 1.0814679861068726,
                "y": 0.36622950434684753,
                "z": 0.5315228700637817
              }
            },
            {
              "position": {
                "x": 0.9555121064186096,
                "y": 0.37822768092155457,
                "z": 0.5633025169372559
              }
            },
            {
              "position": {
                "x": 0.8356660008430481,
                "y": 0.41521838307380676,
                "z": 0.5938888788223267
              }
            },
            {
              "position": {
                "x": 0.7201263904571533,
                "y": 0.46462082862854004,
                "z": 0.6225272417068481
              }
            },
            {
              "position": {
                "x": 0.5910225510597229,
                "y": 0.49389025568962097,
                "z": 0.6411923170089722
              }
            },
            {
              "position": {
                "x": 0.4663848578929901,
                "y": 0.4383696913719177,
                "z": 0.6350643634796143
              }
            },
            {
              "position": {
                "x": 0.4106064736843109,
                "y": 0.32177218794822693,
                "z": 0.5878584980964661
              }
            },
            {
              "position": {
                "x": 0.4419957101345062,
                "y": 0.22063769400119781,
                "z": 0.4980619251728058
              }
            },
            {
              "position": {
                "x": 0.5193595886230469,
                "y": 0.20002439618110657,
                "z": 0.3994266390800476
              }
            },
            {
              "position": {
                "x": 0.604951798915863,
                "y": 0.2028946578502655,
                "z": 0.3211604356765747
              }
            },
            {
              "position": {
                "x": 0.7043079137802124,
                "y": 0.2168976366519928,
                "z": 0.2303793877363205
              }
            },
            {
              "position": {
                "x": 0.799988329410553,
                "y": 0.23667843639850616,
                "z": 0.14296159148216248
              }
            },
            {
              "position": {
                "x": 0.8961270451545715,
                "y": 0.262624055147171,
                "z": 0.05511828884482384
              }
            },
            {
              "position": {
                "x": 0.9916448593139648,
                "y": 0.29085248708724976,
                "z": -0.03246936574578285
              }
            },
            {
              "position": {
                "x": 1.0860130786895752,
                "y": 0.3209856152534485,
                "z": -0.11934712529182434
              }
            },
            {
              "position": {
                "x": 1.180847406387329,
                "y": 0.35542604327201843,
                "z": -0.20677317678928375
              }
            },
            {
              "position": {
                "x": 1.2693040370941162,
                "y": 0.3921603858470917,
                "z": -0.2882111072540283
              }
            },
            {
              "position": {
                "x": 1.4059876203536987,
                "y": 0.46095237135887146,
                "z": -0.41374802589416504
              }
            },
            {
              "position": {
                "x": 1.475585699081421,
                "y": 0.4834422171115875,
                "z": -0.4776146709918976
              }
            },
            {
              "position": {
                "x": 1.5,
                "y": 0.20000000298023224,
                "z": -0.5
              }
            }
          ],
          "scale": 1.0,
          "colorId": 1
        }
      ],
      "pinsData": [
        {
          "position": {
            "x": -0.5,
            "z": 1.5
          },
          "isLocked": 1
        },
        {
          "position": {
            "x": 1.5,
            "z": 0.5
          }
        },
        {
          "position": {
            "x": 1.5,
            "z": -0.5
          }
        },
        {
          "position": {
            "x": -0.5899658203125,
            "z": 1.8199996948242188
          }
        },
        {
          "position": {
            "x": -0.5899658203125,
            "z": 1.8199996948242188
          }
        }
      ],
      "colorId": 1
    },
    {
      "listParticles": [
        {
          "particles": [
            {
              "position": {
                "x": -0.5,
                "y": 0.20000000298023224,
                "z": -1.4999942779541016
              }
            },
            {
              "position": {
                "x": -0.4854016900062561,
                "y": 0.43145468831062317,
                "z": -1.3891270160675049
              }
            },
            {
              "position": {
                "x": -0.47567853331565857,
                "y": 0.4232873320579529,
                "z": -1.320669412612915
              }
            },
            {
              "position": {
                "x": -0.45565497875213623,
                "y": 0.4099806249141693,
                "z": -1.1804863214492798
              }
            },
            {
              "position": {
                "x": -0.4386712610721588,
                "y": 0.4015848934650421,
                "z": -1.038189172744751
              }
            },
            {
              "position": {
                "x": -0.4486728310585022,
                "y": 0.3596491813659668,
                "z": -0.895435094833374
              }
            },
            {
              "position": {
                "x": -0.5372697710990906,
                "y": 0.30711793899536133,
                "z": -0.7856006622314453
              }
            },
            {
              "position": {
                "x": -0.6648781895637512,
                "y": 0.3308260440826416,
                "z": -0.70503830909729
              }
            },
            {
              "position": {
                "x": -0.7307003140449524,
                "y": 0.3553484380245209,
                "z": -0.5765844583511353
              }
            },
            {
              "position": {
                "x": -0.7930613160133362,
                "y": 0.38179001212120056,
                "z": -0.4465758502483368
              }
            },
            {
              "position": {
                "x": -0.8662842512130737,
                "y": 0.3953407406806946,
                "z": -0.3159964382648468
              }
            },
            {
              "position": {
                "x": -0.9726061224937439,
                "y": 0.3258989453315735,
                "z": -0.22880585491657257
              }
            },
            {
              "position": {
                "x": -1.0827161073684692,
                "y": 0.2265399843454361,
                "z": -0.25365138053894043
              }
            },
            {
              "position": {
                "x": -1.1642365455627441,
                "y": 0.20002441108226776,
                "z": -0.37793201208114624
              }
            },
            {
              "position": {
                "x": -1.167718529701233,
                "y": 0.24204851686954498,
                "z": -0.5253067016601562
              }
            },
            {
              "position": {
                "x": -1.168178915977478,
                "y": 0.37682342529296875,
                "z": -0.5794849991798401
              }
            },
            {
              "position": {
                "x": -1.1636990308761597,
                "y": 0.5184770822525024,
                "z": -0.5127792954444885
              }
            },
            {
              "position": {
                "x": -1.1928783655166626,
                "y": 0.568327784538269,
                "z": -0.36450397968292236
              }
            },
            {
              "position": {
                "x": -1.2465318441390991,
                "y": 0.5389958620071411,
                "z": -0.22170725464820862
              }
            },
            {
              "position": {
                "x": -1.2986980676651,
                "y": 0.5103136897087097,
                "z": -0.08270056545734406
              }
            },
            {
              "position": {
                "x": -1.3515069484710693,
                "y": 0.48751065135002136,
                "z": 0.05545269697904587
              }
            },
            {
              "position": {
                "x": -1.4258570671081543,
                "y": 0.46005019545555115,
                "z": 0.2644140124320984
              }
            },
            {
              "position": {
                "x": -1.4856053590774536,
                "y": 0.48138776421546936,
                "z": 0.45406174659729004
              }
            },
            {
              "position": {
                "x": -1.5,
                "y": 0.20000000298023224,
                "z": 0.5
              }
            }
          ],
          "scale": 1.0
        }
      ],
      "pinsData": [
        {
          "position": {
            "x": -0.5,
            "z": -1.5
          },
          "isLocked": 1
        },
        {
          "position": {
            "x": -1.5,
            "z": 0.5
          }
        }
      ],
      "colorId": 3
    },
    {
      "listParticles": [
        {
          "particles": [
            {
              "position": {
                "x": 0.4999699592590332,
                "y": 0.20000000298023224,
                "z": -0.49999427795410156
              }
            },
            {
              "position": {
                "x": 0.5243562459945679,
                "y": 0.4815451502799988,
                "z": -0.45981085300445557
              }
            },
            {
              "position": {
                "x": 0.5606490969657898,
                "y": 0.46785756945610046,
                "z": -0.4001290500164032
              }
            },
            {
              "position": {
                "x": 0.6004250049591064,
                "y": 0.49856239557266235,
                "z": -0.33505770564079285
              }
            },
            {
              "position": {
                "x": 0.6410772800445557,
                "y": 0.5218810439109802,
                "z": -0.268716037273407
              }
            },
            {
              "position": {
                "x": 0.6814594864845276,
                "y": 0.5231128334999084,
                "z": -0.19744622707366943
              }
            },
            {
              "position": {
                "x": 0.8300877809524536,
                "y": 0.5141597986221313,
                "z": 0.08808743953704834
              }
            },
            {
              "position": {
                "x": 0.8679620027542114,
                "y": 0.5172824859619141,
                "z": 0.15962836146354675
              }
            },
            {
              "position": {
                "x": 0.9047440886497498,
                "y": 0.523226261138916,
                "z": 0.2329271286725998
              }
            },
            {
              "position": {
                "x": 0.9791937470436096,
                "y": 0.5383495092391968,
                "z": 0.3785697817802429
              }
            },
            {
              "position": {
                "x": 1.0153826475143433,
                "y": 0.5484036803245544,
                "z": 0.4524295926094055
              }
            },
            {
              "position": {
                "x": 1.0515272617340088,
                "y": 0.560796320438385,
                "z": 0.5261657238006592
              }
            },
            {
              "position": {
                "x": 1.1616437435150146,
                "y": 0.5257304906845093,
                "z": 0.7444465160369873
              }
            },
            {
              "position": {
                "x": 1.2360100746154785,
                "y": 0.5009674429893494,
                "z": 0.8865507245063782
              }
            },
            {
              "position": {
                "x": 1.2730982303619385,
                "y": 0.48977944254875183,
                "z": 0.9575062990188599
              }
            },
            {
              "position": {
                "x": 1.3467202186584473,
                "y": 0.46192705631256104,
                "z": 1.097846269607544
              }
            },
            {
              "position": {
                "x": 1.4179811477661133,
                "y": 0.43101778626441956,
                "z": 1.236621618270874
              }
            },
            {
              "position": {
                "x": 1.4536845684051514,
                "y": 0.4207691550254822,
                "z": 1.3052235841751099
              }
            },
            {
              "position": {
                "x": 1.4999704360961914,
                "y": 0.20000000298023224,
                "z": 1.5
              }
            }
          ],
          "scale": 1.0
        },
        {
          "particles": [
            {
              "position": {
                "x": 1.4999308586120605,
                "y": 0.2023579627275467,
                "z": 1.4997763633728027
              }
            },
            {
              "position": {
                "x": 1.355434775352478,
                "y": 0.47618287801742554,
                "z": 1.6505160331726074
              }
            },
            {
              "position": {
                "x": 1.238178014755249,
                "y": 0.510552167892456,
                "z": 1.7462151050567627
              }
            },
            {
              "position": {
                "x": 0.9902086853981018,
                "y": 0.5350909233093262,
                "z": 1.9259005784988403
              }
            },
            {
              "position": {
                "x": 0.8005620241165161,
                "y": 0.5634016394615173,
                "z": 2.0547890663146973
              }
            },
            {
              "position": {
                "x": 0.6718915700912476,
                "y": 0.5917965769767761,
                "z": 2.1397273540496826
              }
            },
            {
              "position": {
                "x": 0.5214967727661133,
                "y": 0.6015417575836182,
                "z": 2.20889949798584
              }
            },
            {
              "position": {
                "x": 0.3637550175189972,
                "y": 0.5956972241401672,
                "z": 2.2520201206207275
              }
            },
            {
              "position": {
                "x": 0.22278766334056854,
                "y": 0.530754029750824,
                "z": 2.3011317253112793
              }
            },
            {
              "position": {
                "x": 0.16382437944412231,
                "y": 0.37973201274871826,
                "z": 2.321437358856201
              }
            },
            {
              "position": {
                "x": 0.22316974401474,
                "y": 0.2477937787771225,
                "z": 2.283583641052246
              }
            },
            {
              "position": {
                "x": 0.34199804067611694,
                "y": 0.19816705584526062,
                "z": 2.1990013122558594
              }
            },
            {
              "position": {
                "x": 0.49833521246910095,
                "y": 0.19171303510665894,
                "z": 2.1584248542785645
              }
            },
            {
              "position": {
                "x": 0.63775235414505,
                "y": 0.2460567206144333,
                "z": 2.1404666900634766
              }
            },
            {
              "position": {
                "x": 0.6587449312210083,
                "y": 0.39985403418540955,
                "z": 2.0995914936065674
              }
            },
            {
              "position": {
                "x": 0.5351735949516296,
                "y": 0.5220444202423096,
                "z": 2.0771188735961914
              }
            },
            {
              "position": {
                "x": 0.3673718571662903,
                "y": 0.5492894053459167,
                "z": 2.0886523723602295
              }
            },
            {
              "position": {
                "x": 0.2051267921924591,
                "y": 0.5565129518508911,
                "z": 2.1100504398345947
              }
            },
            {
              "position": {
                "x": 0.05393477901816368,
                "y": 0.5279615521430969,
                "z": 2.1833879947662354
              }
            },
            {
              "position": {
                "x": -0.09139283001422882,
                "y": 0.5000235438346863,
                "z": 2.2664988040924072
              }
            },
            {
              "position": {
                "x": -0.23691928386688232,
                "y": 0.4774150848388672,
                "z": 2.348188877105713
              }
            },
            {
              "position": {
                "x": -0.38159406185150146,
                "y": 0.4573655128479004,
                "z": 2.4323863983154297
              }
            },
            {
              "position": {
                "x": -0.45220813155174255,
                "y": 0.4807305335998535,
                "z": 2.473580837249756
              }
            },
            {
              "position": {
                "x": -0.5000300407409668,
                "y": 0.20000000298023224,
                "z": 2.5000057220458984
              }
            }
          ],
          "scale": 1.0
        }
      ],
      "pinsData": [
        {
          "position": {
            "x": 0.5,
            "z": -0.5
          }
        },
        {
          "position": {
            "x": 1.5,
            "z": 1.5
          }
        },
        {
          "position": {
            "x": -0.5,
            "z": 2.5
          }
        }
      ]
    }
  ],
  "indexLockData": [
    "b'\\x01\\x02\\x00\\x03'"
  ]
}